sparkplug_videos/__init__.py
sparkplug_videos/apps.py
sparkplug_videos/enums/__init__.py
sparkplug_videos/enums/client.py
sparkplug_videos/migrations/0001_initial.py
sparkplug_videos/migrations/__init__.py
sparkplug_videos/models/__init__.py
sparkplug_videos/models/video.py
sparkplug_videos/permissions/__init__.py
sparkplug_videos/permissions/video.py
sparkplug_videos/serializers/__init__.py
sparkplug_videos/serializers/video_expanded.py
sparkplug_videos/serializers/video_teaser.py
sparkplug_videos/serializers/video_write.py
sparkplug_videos/services/__init__.py
sparkplug_videos/services/optimize_video.py
sparkplug_videos/signals.py
sparkplug_videos/tasks/__init__.py
sparkplug_videos/tasks/process_video.py
sparkplug_videos/uploads.py
sparkplug_videos/urls.py
sparkplug_videos/views/__init__.py
sparkplug_videos/views/video.py
sparkplug_api_videos-1.0.3.dist-info/METADATA
sparkplug_api_videos-1.0.3.dist-info/WHEEL
sparkplug_api_videos-1.0.3.dist-info/RECORD
