Metadata-Version: 2.3
Name: sparkplug-api-videos
Version: 1.0.3
Summary: Video package for Sparkplug apps
License: MIT
Author: Sparkplug Marcus
Author-email: sparkplugmarcus@gmail.com
Requires-Python: >=3.10,<4.0
Classifier: License :: OSI Approved :: MIT License
Classifier: Programming Language :: Python :: 3
Classifier: Programming Language :: Python :: 3.10
Classifier: Programming Language :: Python :: 3.11
Classifier: Programming Language :: Python :: 3.12
Classifier: Programming Language :: Python :: 3.13
Requires-Dist: sparkplug-api-core (>=1.0.11,<1.1.0)
